humanmouse/__init__.py
humanmouse/__version__.py
humanmouse/cli.py
humanmouse/py.typed
humanmouse/controllers/__init__.py
humanmouse/controllers/mouse_controller.py
humanmouse/core/__init__.py
humanmouse/core/exceptions.py
humanmouse/core/interfaces.py
humanmouse/core/trajectory.py
humanmouse/models/__init__.py
humanmouse/models/trajectory_model.py
humanmouse/models/data/mouse_model.pkl
humanmovemouse-1.0.0.dist-info/licenses/LICENSE
humanmovemouse-1.0.0.dist-info/METADATA
humanmovemouse-1.0.0.dist-info/WHEEL
humanmovemouse-1.0.0.dist-info/entry_points.txt
humanmovemouse-1.0.0.dist-info/top_level.txt
humanmovemouse-1.0.0.dist-info/RECORD
