Metadata-Version: 2.4
Name: HumanMoveMouse
Version: 1.0.0
Summary: A human-like mouse movement automation tool based on real trajectory data
Home-page: https://github.com/TomokotoKiyoshi/HumanMoveMouse
Author: TomokotoKiyoshi
Author-email: 
License: MIT
Project-URL: Homepage, https://github.com/TomokotoKiyoshi/HumanMoveMouse
Project-URL: Documentation, https://humanmovemouse.readthedocs.io
Project-URL: Repository, https://github.com/TomokotoKiyoshi/HumanMoveMouse.git
Project-URL: Bug Tracker, https://github.com/TomokotoKiyoshi/HumanMoveMouse/issues
Project-URL: Changelog, https://github.com/TomokotoKiyoshi/HumanMoveMouse/blob/main/CHANGELOG.md
Keywords: mouse,automation,human-like,trajectory,movement,testing,ui-automation
Classifier: Development Status :: 4 - Beta
Classifier: Intended Audience :: Developers
Classifier: Topic :: Software Development :: Libraries :: Python Modules
Classifier: Topic :: Software Development :: Testing
Classifier: Topic :: System :: Monitoring
Classifier: License :: OSI Approved :: MIT License
Classifier: Programming Language :: Python :: 3
Classifier: Programming Language :: Python :: 3.8
Classifier: Programming Language :: Python :: 3.9
Classifier: Programming Language :: Python :: 3.10
Classifier: Programming Language :: Python :: 3.11
Classifier: Programming Language :: Python :: 3.12
Classifier: Operating System :: OS Independent
Requires-Python: >=3.8
License-File: LICENSE
Requires-Dist: numpy>=1.20.0
Requires-Dist: pandas>=1.3.0
Requires-Dist: scipy>=1.7.0
Requires-Dist: scikit-learn>=0.24.0
Requires-Dist: pyautogui>=0.9.50
Provides-Extra: dev
Requires-Dist: pytest>=7.0.0; extra == "dev"
Requires-Dist: pytest-cov>=3.0.0; extra == "dev"
Requires-Dist: black>=22.0.0; extra == "dev"
Requires-Dist: flake8>=4.0.0; extra == "dev"
Requires-Dist: mypy>=0.950; extra == "dev"
Requires-Dist: sphinx>=4.0.0; extra == "dev"
Requires-Dist: sphinx-rtd-theme>=1.0.0; extra == "dev"
Provides-Extra: collector
Requires-Dist: pygame>=2.0.0; extra == "collector"
Dynamic: home-page
Dynamic: license-file
Dynamic: requires-python
